cosma_tui/__init__.py
cosma_tui/client.py
cosma_tui/config.py
cosma_tui/error_modal.py
cosma_tui/models.py
cosma_tui/onboarding.py
cosma_tui/tui.py
cosma_tui-0.2.0.dist-info/WHEEL
cosma_tui-0.2.0.dist-info/METADATA
cosma_tui-0.2.0.dist-info/RECORD
