Metadata-Version: 2.3
Name: cosma-tui
Version: 0.2.0
Summary: Cosma TUI
Requires-Dist: niquests>=3.15.2
Requires-Dist: platformdirs>=4.4.0
Requires-Dist: textual>=6.1.0
Requires-Python: >=3.12
